pyformatters_consolidate/__init__.py
pyformatters_consolidate/consolidate.py
pyformatters_consolidate-0.4.87.dist-info/entry_points.txt
pyformatters_consolidate-0.4.87.dist-info/LICENSE
pyformatters_consolidate-0.4.87.dist-info/WHEEL
pyformatters_consolidate-0.4.87.dist-info/METADATA
pyformatters_consolidate-0.4.87.dist-info/RECORD
